[{"model": "EventsApp.sportsimage", "pk": 156, "fields": {"sport": "7futsal", "img": "images/futsal.jpg"}}, {"model": "EventsApp.sportsimage", "pk": 157, "fields": {"sport": "Aerobics", "img": "images/Aerobics.jpg"}}, {"model": "EventsApp.sportsimage", "pk": 158, "fields": {"sport": "Aikido", "img": "images/aikido.jpg"}}, {"model": "EventsApp.sportsimage", "pk": 159, "fields": {"sport": "Amputee Hockey", "img": "images/Amputee_Hockey.jpg"}}, {"model": "EventsApp.sportsimage", "pk": 160, "fields": {"sport": "Archery", "img": "images/archery.jpg"}}, {"model": "EventsApp.sportsimage", "pk": 161, "fields": {"sport": "Axe Throwing", "img": "images/Axe_throwing.jpg"}}, {"model": "EventsApp.sportsimage", "pk": 162, "fields": {"sport": "Badminton", "img": "images/badminton.jpg"}}, {"model": "EventsApp.sportsimage", "pk": 163, "fields": {"sport": "Ball/Floor Hockey", "img": "images/floor_hockey.jpg"}}, {"model": "EventsApp.sportsimage", "pk": 164, "fields": {"sport": "Base Jumping", "img": "images/Base_jumping.jpg"}}, {"model": "EventsApp.sportsimage", "pk": 165, "fields": {"sport": "Basketball", "img": "images/Basketball.jpg"}}, {"model": "EventsApp.sportsimage", "pk": 166, "fields": {"sport": "Beach Soccer", "img": "images/Beach_Soccer.jpg"}}, {"model": "EventsApp.sportsimage", "pk": 167, "fields": {"sport": "Billiards", "img": "images/Billiards.jpg"}}, {"model": "EventsApp.sportsimage", "pk": 168, "fields": {"sport": "Blind Hockey", "img": "images/Blind_Hockey.jpg"}}, {"model": "EventsApp.sportsimage", "pk": 169, "fields": {"sport": "BMX", "img": "images/BMX.jpg"}}, {"model": "EventsApp.sportsimage", "pk": 170, "fields": {"sport": "Board Game", "img": "images/Board_Game.jpg"}}, {"model": "EventsApp.sportsimage", "pk": 171, "fields": {"sport": "Bobsledding", "img": "images/Bobsledding.jpg"}}, {"model": "EventsApp.sportsimage", "pk": 172, "fields": {"sport": "Bocce", "img": "images/Bocce.jpg"}}, {"model": "EventsApp.sportsimage", "pk": 173, "fields": {"sport": "Boss", "img": "images/Multisport_GpxxXmQ.jpg"}}, {"model": "EventsApp.sportsimage", "pk": 174, "fields": {"sport": "Bowling", "img": "images/Bowling.jpg"}}, {"model": "EventsApp.sportsimage", "pk": 175, "fields": {"sport": "Box Lacrosse", "img": "images/Box_Lacrosse.jpg"}}, {"model": "EventsApp.sportsimage", "pk": 176, "fields": {"sport": "Boxing", "img": "images/Boxing.jpg"}}, {"model": "EventsApp.sportsimage", "pk": 177, "fields": {"sport": "Bubble Soccer", "img": "images/Bubble_Soccer.jpg"}}, {"model": "EventsApp.sportsimage", "pk": 178, "fields": {"sport": "Canoeing", "img": "images/Canoeing.jpg"}}, {"model": "EventsApp.sportsimage", "pk": 179, "fields": {"sport": "Cart", "img": "images/Cart.jpg"}}, {"model": "EventsApp.sportsimage", "pk": 180, "fields": {"sport": "Climbing", "img": "images/Climbing.jpg"}}, {"model": "EventsApp.sportsimage", "pk": 181, "fields": {"sport": "Cricket", "img": "images/Cricket.jpg"}}, {"model": "EventsApp.sportsimage", "pk": 182, "fields": {"sport": "Cross Country Running", "img": "images/Cross_Country_Running.jpg"}}, {"model": "EventsApp.sportsimage", "pk": 183, "fields": {"sport": "Cross Country Skiing", "img": "images/Cross_Country_Skiing.jpg"}}, {"model": "EventsApp.sportsimage", "pk": 184, "fields": {"sport": "Crossfit", "img": "images/Crossfit.jpg"}}, {"model": "EventsApp.sportsimage", "pk": 185, "fields": {"sport": "Curling", "img": "images/Curling.jpg"}}, {"model": "EventsApp.sportsimage", "pk": 186, "fields": {"sport": "Dance", "img": "images/Dance.jpg"}}, {"model": "EventsApp.sportsimage", "pk": 187, "fields": {"sport": "Darts", "img": "images/Darts.jpg"}}, {"model": "EventsApp.sportsimage", "pk": 188, "fields": {"sport": "Discus", "img": "images/Discus.jpg"}}, {"model": "EventsApp.sportsimage", "pk": 189, "fields": {"sport": "Disk Golf", "img": "images/Disk_Golf.jpg"}}, {"model": "EventsApp.sportsimage", "pk": 190, "fields": {"sport": "Diving", "img": "images/Diving.jpg"}}, {"model": "EventsApp.sportsimage", "pk": 191, "fields": {"sport": "Dodgeball", "img": "images/Dodgeball.png"}}, {"model": "EventsApp.sportsimage", "pk": 192, "fields": {"sport": "Dog Sledding", "img": "images/Dog_Sledding.jpg"}}, {"model": "EventsApp.sportsimage", "pk": 193, "fields": {"sport": "Downhill/Alpine", "img": "images/Downhill_skiing.jpg"}}, {"model": "EventsApp.sportsimage", "pk": 194, "fields": {"sport": "Dragon Boat", "img": "images/Dragon_Boating.jpg"}}, {"model": "EventsApp.sportsimage", "pk": 195, "fields": {"sport": "Efoiling", "img": "images/Efoiling.jpg"}}, {"model": "EventsApp.sportsimage", "pk": 196, "fields": {"sport": "Equestrian", "img": "images/Equestrian-Horseback_Riding.jpg"}}, {"model": "EventsApp.sportsimage", "pk": 197, "fields": {"sport": "Fastball", "img": "images/Fastball.jpg"}}, {"model": "EventsApp.sportsimage", "pk": 198, "fields": {"sport": "Fencing", "img": "images/Fencing.jpg"}}, {"model": "EventsApp.sportsimage", "pk": 199, "fields": {"sport": "Field Hockey", "img": "images/Field_Hockey.jpg"}}, {"model": "EventsApp.sportsimage", "pk": 200, "fields": {"sport": "Field Lacrosse", "img": "images/Field_Lacrosse.jpg"}}, {"model": "EventsApp.sportsimage", "pk": 201, "fields": {"sport": "Figure Skating", "img": "images/Figure_Skating.jpg"}}, {"model": "EventsApp.sportsimage", "pk": 202, "fields": {"sport": "First Responding", "img": "images/First_Responding.jpg"}}, {"model": "EventsApp.sportsimage", "pk": 203, "fields": {"sport": "Fishing", "img": "images/Fishing-Angling.jpg"}}, {"model": "EventsApp.sportsimage", "pk": 204, "fields": {"sport": "Fist Ball", "img": "images/Fist_Ball.jpg"}}, {"model": "EventsApp.sportsimage", "pk": 205, "fields": {"sport": "Flag Football", "img": "images/flag_football.jpg"}}, {"model": "EventsApp.sportsimage", "pk": 206, "fields": {"sport": "Football", "img": "images/Football.jpg"}}, {"model": "EventsApp.sportsimage", "pk": 207, "fields": {"sport": "Golf", "img": "images/Golf.jpg"}}, {"model": "EventsApp.sportsimage", "pk": 208, "fields": {"sport": "Gymnastics", "img": "images/Gymnastics.jpg"}}, {"model": "EventsApp.sportsimage", "pk": 209, "fields": {"sport": "Haloball", "img": "images/Halo_Ball.jpg"}}, {"model": "EventsApp.sportsimage", "pk": 210, "fields": {"sport": "Handball", "img": "images/Handball.jpg"}}, {"model": "EventsApp.sportsimage", "pk": 211, "fields": {"sport": "High Jump", "img": "images/High_Jump.jpg"}}, {"model": "EventsApp.sportsimage", "pk": 212, "fields": {"sport": "Hurling", "img": "images/Hurling-Camogie.jpg"}}, {"model": "EventsApp.sportsimage", "pk": 213, "fields": {"sport": "Ice Dragon Boating", "img": "images/Ice_Dragon_Boating.jpg"}}, {"model": "EventsApp.sportsimage", "pk": 214, "fields": {"sport": "Ice Hockey", "img": "images/Ice_Hockey.jpg"}}, {"model": "EventsApp.sportsimage", "pk": 215, "fields": {"sport": "Ice Skating", "img": "images/Ice_Skating.jpg"}}, {"model": "EventsApp.sportsimage", "pk": 216, "fields": {"sport": "Indoor Skydiving", "img": "images/indoor_skydiving.jpg"}}, {"model": "EventsApp.sportsimage", "pk": 217, "fields": {"sport": "Inline/Roller Hockey", "img": "images/Inline_hockey.jpg"}}, {"model": "EventsApp.sportsimage", "pk": 218, "fields": {"sport": "Javelin", "img": "images/Javelin.jpg"}}, {"model": "EventsApp.sportsimage", "pk": 219, "fields": {"sport": "Jiu Jitsu", "img": "images/Jiu_Jitsu.jpg"}}, {"model": "EventsApp.sportsimage", "pk": 220, "fields": {"sport": "Judo", "img": "images/Judo.jpg"}}, {"model": "EventsApp.sportsimage", "pk": 221, "fields": {"sport": "Karate", "img": "images/Karate.jpg"}}, {"model": "EventsApp.sportsimage", "pk": 222, "fields": {"sport": "Kayaking", "img": "images/Kayaking.jpg"}}, {"model": "EventsApp.sportsimage", "pk": 223, "fields": {"sport": "Lawn Bowling", "img": "images/Lawn_Bowling.jpg"}}, {"model": "EventsApp.sportsimage", "pk": 224, "fields": {"sport": "Luge", "img": "images/Luge.jpg"}}, {"model": "EventsApp.sportsimage", "pk": 225, "fields": {"sport": "Manhunt", "img": "images/Manhunt.jpg"}}, {"model": "EventsApp.sportsimage", "pk": 226, "fields": {"sport": "Marathoning", "img": "images/Marathoning.jpg"}}, {"model": "EventsApp.sportsimage", "pk": 228, "fields": {"sport": "Mauy Thai/Kick Boxing", "img": "images/Mauy_Thai-Kick_Boxing-Savate.jpg"}}, {"model": "EventsApp.sportsimage", "pk": 229, "fields": {"sport": "Medtation", "img": "images/Meditation.jpg"}}, {"model": "EventsApp.sportsimage", "pk": 230, "fields": {"sport": "Mixed Martial Arts", "img": "images/Mixed_Martial_Arts.jpg"}}, {"model": "EventsApp.sportsimage", "pk": 231, "fields": {"sport": "Motorcross", "img": "images/motorcross.jpg"}}, {"model": "EventsApp.sportsimage", "pk": 232, "fields": {"sport": "Mudder", "img": "images/Mudder.jpg"}}, {"model": "EventsApp.sportsimage", "pk": 233, "fields": {"sport": "Multisport", "img": "images/Multisport.jpg"}}, {"model": "EventsApp.sportsimage", "pk": 234, "fields": {"sport": "Nerf War", "img": "images/Nerf_War.jpg"}}, {"model": "EventsApp.sportsimage", "pk": 235, "fields": {"sport": "Ninja Camp", "img": "images/Ninja_Camp.jpg"}}, {"model": "EventsApp.sportsimage", "pk": 236, "fields": {"sport": "Outdoor Skydiving", "img": "images/Outdoor_Skydiving.jpg"}}, {"model": "EventsApp.sportsimage", "pk": 237, "fields": {"sport": "Paddle Boarding", "img": "images/Paddle_Boarding.jpg"}}, {"model": "EventsApp.sportsimage", "pk": 238, "fields": {"sport": "Paintball", "img": "images/Paintball.jpg"}}, {"model": "EventsApp.sportsimage", "pk": 239, "fields": {"sport": "Panic Room", "img": "images/Panic_Room.jpg"}}, {"model": "EventsApp.sportsimage", "pk": 240, "fields": {"sport": "Para Soccer", "img": "images/Para_Soccer_kpNgaZO.jpg"}}, {"model": "EventsApp.sportsimage", "pk": 241, "fields": {"sport": "ParaFencing", "img": "images/Para_fencing.jpg"}}, {"model": "EventsApp.sportsimage", "pk": 242, "fields": {"sport": "ParaGliding/ParaSailing", "img": "images/parasailing.jpg"}}, {"model": "EventsApp.sportsimage", "pk": 243, "fields": {"sport": "Paraskiing", "img": "images/Para_Skiing.jpg"}}, {"model": "EventsApp.sportsimage", "pk": 244, "fields": {"sport": "ParaSoccer", "img": "images/Para_Soccer.jpg"}}, {"model": "EventsApp.sportsimage", "pk": 245, "fields": {"sport": "Park Program", "img": "images/Park_Program.jpg"}}, {"model": "EventsApp.sportsimage", "pk": 246, "fields": {"sport": "Parkour", "img": "images/Parkour.jpg"}}, {"model": "EventsApp.sportsimage", "pk": 247, "fields": {"sport": "Pickleball", "img": "images/Pickleball.jpg"}}, {"model": "EventsApp.sportsimage", "pk": 248, "fields": {"sport": "Pole Vault", "img": "images/Pole_Vault.jpg"}}, {"model": "EventsApp.sportsimage", "pk": 249, "fields": {"sport": "Polo", "img": "images/Polo.jpg"}}, {"model": "EventsApp.sportsimage", "pk": 250, "fields": {"sport": "Rafting", "img": "images/Rafting.jpg"}}, {"model": "EventsApp.sportsimage", "pk": 251, "fields": {"sport": "Red Rover", "img": "images/Red_Rover.jpg"}}, {"model": "EventsApp.sportsimage", "pk": 252, "fields": {"sport": "Ringette", "img": "images/Ringette.jpg"}}, {"model": "EventsApp.sportsimage", "pk": 253, "fields": {"sport": "Roller Derby", "img": "images/Roller_Derby.jpg"}}, {"model": "EventsApp.sportsimage", "pk": 254, "fields": {"sport": "Round Ball", "img": "images/Round_Ball-Spikeball.jpg"}}, {"model": "EventsApp.sportsimage", "pk": 255, "fields": {"sport": "Rowing", "img": "images/Rowing.jpg"}}, {"model": "EventsApp.sportsimage", "pk": 256, "fields": {"sport": "Rugby", "img": "images/Rugby.jpg"}}, {"model": "EventsApp.sportsimage", "pk": 257, "fields": {"sport": "Running", "img": "images/Running.jpg"}}, {"model": "EventsApp.sportsimage", "pk": 258, "fields": {"sport": "Sailing/Boating", "img": "images/Sailing-Boating.jpg"}}, {"model": "EventsApp.sportsimage", "pk": 259, "fields": {"sport": "Savate", "img": "images/Savate.jpg"}}, {"model": "EventsApp.sportsimage", "pk": 260, "fields": {"sport": "Scuba", "img": "images/Scuba.jpg"}}, {"model": "EventsApp.sportsimage", "pk": 261, "fields": {"sport": "Shinny", "img": "images/Shinny.jpg"}}, {"model": "EventsApp.sportsimage", "pk": 262, "fields": {"sport": "Shooting", "img": "images/Shooting.jpg"}}, {"model": "EventsApp.sportsimage", "pk": 263, "fields": {"sport": "Shot Put", "img": "images/Shot_Put.jpg"}}, {"model": "EventsApp.sportsimage", "pk": 264, "fields": {"sport": "Sitting Volleyball", "img": "images/Sitting_Volleyball.jpg"}}, {"model": "EventsApp.sportsimage", "pk": 265, "fields": {"sport": "Skateboarding/Scootering", "img": "images/Skateboarding-Scootering.jpg"}}, {"model": "EventsApp.sportsimage", "pk": 266, "fields": {"sport": "Skiing", "img": "images/Ski_Jump.jpg"}}, {"model": "EventsApp.sportsimage", "pk": 267, "fields": {"sport": "Skim Boarding", "img": "images/Skim_Boarding.jpg"}}, {"model": "EventsApp.sportsimage", "pk": 268, "fields": {"sport": "Sledge Hockey", "img": "images/Sledge_Hockey.jpg"}}, {"model": "EventsApp.sportsimage", "pk": 269, "fields": {"sport": "Snowboarding", "img": "images/snowboarding.jpg"}}, {"model": "EventsApp.sportsimage", "pk": 270, "fields": {"sport": "Soccer", "img": "images/Soccer.jpg"}}, {"model": "EventsApp.sportsimage", "pk": 271, "fields": {"sport": "Soccer Baseball", "img": "images/Soccer_Baseball.jpg"}}, {"model": "EventsApp.sportsimage", "pk": 272, "fields": {"sport": "Softball", "img": "images/Softball.jpg"}}, {"model": "EventsApp.sportsimage", "pk": 273, "fields": {"sport": "Speed Skating", "img": "images/Speed_Skating.jpg"}}, {"model": "EventsApp.sportsimage", "pk": 274, "fields": {"sport": "Spin", "img": "images/Spin.jpg"}}, {"model": "EventsApp.sportsimage", "pk": 275, "fields": {"sport": "Squash", "img": "images/Squash.jpg"}}, {"model": "EventsApp.sportsimage", "pk": 276, "fields": {"sport": "Stick & Puck", "img": "images/Stick_and_Puck.jpg"}}, {"model": "EventsApp.sportsimage", "pk": 277, "fields": {"sport": "Surfing/Wind Surfing", "img": "images/Surfing.jpg"}}, {"model": "EventsApp.sportsimage", "pk": 278, "fields": {"sport": "Swimming", "img": "images/Swimming.jpg"}}, {"model": "EventsApp.sportsimage", "pk": 279, "fields": {"sport": "Synchro Swimming", "img": "images/Synchro_Swimming.jpg"}}, {"model": "EventsApp.sportsimage", "pk": 280, "fields": {"sport": "T-Ball", "img": "images/T-Ball.jpg"}}, {"model": "EventsApp.sportsimage", "pk": 281, "fields": {"sport": "Table Tennis", "img": "images/Table_Tennis.jpg"}}, {"model": "EventsApp.sportsimage", "pk": 282, "fields": {"sport": "Tae Kwondo", "img": "images/Tae_Kwondo.jpg"}}, {"model": "EventsApp.sportsimage", "pk": 283, "fields": {"sport": "Tchoukball", "img": "images/Tchoukball.jpg"}}, {"model": "EventsApp.sportsimage", "pk": 284, "fields": {"sport": "Tennis", "img": "images/Tennis.jpg"}}, {"model": "EventsApp.sportsimage", "pk": 285, "fields": {"sport": "Touch Football", "img": "images/Touch_Football.jpg"}}, {"model": "EventsApp.sportsimage", "pk": 286, "fields": {"sport": "Track Running", "img": "images/Track_Running.jpg"}}, {"model": "EventsApp.sportsimage", "pk": 287, "fields": {"sport": "Trampolining", "img": "images/Trampolining.jpg"}}, {"model": "EventsApp.sportsimage", "pk": 288, "fields": {"sport": "Trekking", "img": "images/Trekking.walking.hiking.jpg"}}, {"model": "EventsApp.sportsimage", "pk": 289, "fields": {"sport": "Ultimate Frisbee", "img": "images/Ultimate_Frisbee_oiQuSSs.jpg"}}, {"model": "EventsApp.sportsimage", "pk": 290, "fields": {"sport": "Ultimate Para-frisbee", "img": "images/Ultimate_Frisbee.jpg"}}, {"model": "EventsApp.sportsimage", "pk": 291, "fields": {"sport": "Volleyball", "img": "images/Volleyball.jpg"}}, {"model": "EventsApp.sportsimage", "pk": 292, "fields": {"sport": "Water Aerobics", "img": "images/Water_Aerobics.png"}}, {"model": "EventsApp.sportsimage", "pk": 293, "fields": {"sport": "Water Polo", "img": "images/Water_Polo.jpg"}}, {"model": "EventsApp.sportsimage", "pk": 294, "fields": {"sport": "Weight Training", "img": "images/Weight_Training.jpg"}}, {"model": "EventsApp.sportsimage", "pk": 295, "fields": {"sport": "Wheelchair Archery", "img": "images/Wheelchair_archery.jpg"}}, {"model": "EventsApp.sportsimage", "pk": 296, "fields": {"sport": "Wheelchair Badminton", "img": "images/Wheelchair_Badminton.jpg"}}, {"model": "EventsApp.sportsimage", "pk": 297, "fields": {"sport": "Wheelchair Basketball", "img": "images/Wheelchair_Basketball.jpg"}}, {"model": "EventsApp.sportsimage", "pk": 298, "fields": {"sport": "Wheelchair Fencing", "img": "images/Wheelchair_fencing.jpg"}}, {"model": "EventsApp.sportsimage", "pk": 299, "fields": {"sport": "Wheelchair Rugby", "img": "images/Wheelchair_Rugby.jpg"}}, {"model": "EventsApp.sportsimage", "pk": 300, "fields": {"sport": "Wheelchair Table Tennis", "img": "images/Wheelchair_Table_Tennis.jpg"}}, {"model": "EventsApp.sportsimage", "pk": 301, "fields": {"sport": "Wheelchair Tennis", "img": "images/Wheelchair_Tennis.jpg"}}, {"model": "EventsApp.sportsimage", "pk": 302, "fields": {"sport": "Wrestling", "img": "images/wrestling.jpg"}}, {"model": "EventsApp.sportsimage", "pk": 303, "fields": {"sport": "Yoga", "img": "images/Yoga.jpg"}}]